[
  {
    "title": "Morocco down Netherlands on penalties to reach last 16",
    "url": "https://gbcode.rthk.hk/TuniS/news.rthk.hk/rthk/en/component/k2/1860479-20260630.htm?spTabChangeable=0",
    "source": "香港電台",
    "time": "2026-06-30 13:03"
  },
  {
    "title": "A metropolis stuck in gridlock",
    "url": "https://www.chinadailyasia.com/article/635719",
    "source": "chinadailyhk",
    "time": "2026-06-30 12:56"
  },
  {
    "title": "Perfect Diary expands into Sephora China",
    "url": "https://www.globalcosmeticsnews.com/perfect-diary-expands-into-sephora-china/",
    "source": "Global Cosmetics News",
    "time": "2026-06-30 13:09"
  },
  {
    "title": "Chinese billionaire Guo Wengui gets 30 years in US prison for huge fraud",
    "url": "https://www.aljazeera.com/news/2026/6/30/chinese-billionaire-guo-wengui-gets-30-years-in-us-prison-for-huge-fraud",
    "source": "Al Jazeera",
    "time": "2026-06-30 13:28"
  },
  {
    "title": "US retailers moved China orders earlier, pushing up freight costs",
    "url": "https://mezha.net/eng/bukvy/7fba079f_us_retailers_moved/",
    "source": "Межа. Новини України",
    "time": "2026-06-30 13:40"
  },
  {
    "title": "China holds concert to celebrate 105th founding anniversary of CPC",
    "url": "https://news.cgtn.com/news/2026-06-30/China-holds-concert-to-celebrate-105th-founding-anniversary-of-CPC-1OomlsRWRZC/p.html",
    "source": "CGTN",
    "time": "2026-06-30 13:04"
  },
  {
    "title": "CATL, CALB among backers of new China BESS industry payment and contracting initiative",
    "url": "https://www.energy-storage.news/catl-calb-among-backers-of-new-china-bess-industry-payment-and-contracting-initiative/",
    "source": "Energy-Storage.News",
    "time": "2026-06-30 12:52"
  },
  {
    "title": "Opals v China live & free on 9Network",
    "url": "https://www.australia.basketball/news/4528458/opals-v-china-live-free-on-9network",
    "source": "Basketball Australia",
    "time": "2026-06-30 13:11"
  },
  {
    "title": "Thailand Tourism Authority on Alert as China–Japan Travel Revival Triggers Major Shift in Asian Tourist Flows",
    "url": "https://www.travelandtourworld.com/news/article/3q94gmbtk6x4/",
    "source": "Travel And Tour World",
    "time": "2026-06-30 13:26"
  },
  {
    "title": "44 Chinese vessels spotted in WPS from June 23-29",
    "url": "https://www.pna.gov.ph/articles/1278322",
    "source": "Philippine News Agency",
    "time": "2026-06-30 13:34"
  },
  {
    "title": "Chinese Electric Vehicles Pull Into The Lead",
    "url": "https://mshale.com/7ca801b4/49afd6d0jMQr1QRIp90",
    "source": "Mshale",
    "time": "2026-06-30 12:59"
  },
  {
    "title": "China's move amid falling gold prices",
    "url": "https://news.laodong.vn/tien-te-dau-tu/dong-thai-cua-trung-quoc-giua-luc-gia-vang-lao-doc-1727371.ldo",
    "source": "Laodong.vn",
    "time": "2026-06-30 12:53"
  },
  {
    "title": "Jeep to launch China-built 4x4 flagship and two Stellantis-based small SUVs in Europe",
    "url": "https://www.londondaily.news/jeep-to-launch-china-built-4x4-flagship-and-two-stellantis-based-small-suvs-in-europe/",
    "source": "London Daily News",
    "time": "2026-06-30 13:25"
  },
  {
    "title": "US Under Secretary Jacob Helberg Highlights India's Advantage Over China In AI",
    "url": "https://www.ndtv.com/video/us-under-secretary-jacob-helberg-highlights-india-s-advantage-over-china-in-ai-1120303",
    "source": "NDTV",
    "time": "2026-06-30 13:04"
  },
  {
    "title": "Venezuela Earthquakes: China to send another 100 million yuan of humanitarian aid",
    "url": "https://news.cgtn.com/news/2026-06-30/VHJhbnNjcmlwdDkxMzMy/index.html",
    "source": "CGTN",
    "time": "2026-06-30 12:57"
  },
  {
    "title": "Thailand Watches China's Return to Japan as Competition for Chinese Travellers Intensifies Across Asia",
    "url": "https://www.travelandtourworld.com/news/article/nmthd1z3l1tn/",
    "source": "Travel And Tour World",
    "time": "2026-06-30 13:14"
  },
  {
    "title": "Venezuela Earthquakes: Venezuelan expat in China raises more than $10,000 for disaster relief",
    "url": "https://news.cgtn.com/news/2026-06-30/VHJhbnNjcmlwdDkxMzMx/index.html",
    "source": "CGTN",
    "time": "2026-06-30 12:57"
  },
  {
    "title": "Xi backs Belarus sovereignty, Polymarket keeps Xi out-by-2027 odds at 6.25%",
    "url": "https://blockchain.news/news/xi-backs-belarus-sovereignty-polymarket-keeps-xi-out-by-2027-odds-at-625-0hnmm1976sb80",
    "source": "blockchain.news",
    "time": "2026-06-30 12:58"
  }
]